hclient/__init__.py
hclient/api.py
hclient/exceptions.py
hclient/models.py
hclient/sessions.py
hclient/structures.py
hclient-0.0.1.dist-info/WHEEL
hclient-0.0.1.dist-info/METADATA
hclient-0.0.1.dist-info/RECORD
